{
  "Routes": [
    {
      "DownstreamPathTemplate": "/api/Crypto",
      "DownstreamScheme": "https",
      "DownstreamHostAndPorts": [
        {
          "Host": "localhost",
          "Port": 443
        }
      ],
      "UpstreamPathTemplate": "/transaction/api/Crypto",
      "UpstreamHttpMethod": [
        "GET",
        "POST",
        "PUT"
      ],
      "SwaggerKey": "transaction"
    },
    {
      "DownstreamPathTemplate": "/api/Crypto/{id}",
      "DownstreamScheme": "https",
      "DownstreamHostAndPorts": [
        {
          "Host": "localhost",
          "Port": 443
        }
      ],
      "UpstreamPathTemplate": "/transaction/api/Crypto/{id}",
      "UpstreamHttpMethod": [
        "GET",
        "DELETE"
      ],
      "SwaggerKey": "transaction"
    },
    {
      "DownstreamPathTemplate": "/api/Network",
      "DownstreamScheme": "https",
      "DownstreamHostAndPorts": [
        {
          "Host": "localhost",
          "Port": 443
        }
      ],
      "UpstreamPathTemplate": "/transaction/api/Network",
      "UpstreamHttpMethod": [
        "GET",
        "POST",
        "PUT"
      ],
      "SwaggerKey": "transaction"
    },
    {
      "DownstreamPathTemplate": "/api/Network/{id}",
      "DownstreamScheme": "https",
      "DownstreamHostAndPorts": [
        {
          "Host": "localhost",
          "Port": 443
        }
      ],
      "UpstreamPathTemplate": "/transaction/api/Network/{id}",
      "UpstreamHttpMethod": [
        "GET",
        "DELETE"
      ],
      "SwaggerKey": "transaction"
    },
    {
      "DownstreamPathTemplate": "/api/PaymentMethod",
      "DownstreamScheme": "https",
      "DownstreamHostAndPorts": [
        {
          "Host": "localhost",
          "Port": 443
        }
      ],
      "UpstreamPathTemplate": "/transaction/api/PaymentMethod",
      "UpstreamHttpMethod": [
        "GET",
        "POST",
        "PUT"
      ],
      "SwaggerKey": "transaction"
    },
    {
      "DownstreamPathTemplate": "/api/PaymentMethod/by-crypto/{cryptoId}",
      "DownstreamScheme": "https",
      "DownstreamHostAndPorts": [
        {
          "Host": "localhost",
          "Port": 443
        }
      ],
      "UpstreamPathTemplate": "/transaction/api/PaymentMethod/by-crypto/{cryptoId}",
      "UpstreamHttpMethod": [
        "GET"
      ],
      "SwaggerKey": "transaction"
    },
    {
      "DownstreamPathTemplate": "/api/PaymentMethod/{id}",
      "DownstreamScheme": "https",
      "DownstreamHostAndPorts": [
        {
          "Host": "localhost",
          "Port": 443
        }
      ],
      "UpstreamPathTemplate": "/transaction/api/PaymentMethod/{id}",
      "UpstreamHttpMethod": [
        "GET",
        "DELETE"
      ],
      "SwaggerKey": "transaction"
    },
    {
      "DownstreamPathTemplate": "/api/Payments/all",
      "DownstreamScheme": "https",
      "DownstreamHostAndPorts": [
        {
          "Host": "localhost",
          "Port": 443
        }
      ],
      "UpstreamPathTemplate": "/transaction/api/Payments/all",
      "UpstreamHttpMethod": [
        "GET"
      ],
      "SwaggerKey": "transaction"
    },
    {
      "DownstreamPathTemplate": "/api/Referral/summary",
      "DownstreamScheme": "https",
      "DownstreamHostAndPorts": [
        {
          "Host": "localhost",
          "Port": 443
        }
      ],
      "UpstreamPathTemplate": "/transaction/api/Referral/summary",
      "UpstreamHttpMethod": [
        "GET"
      ],
      "SwaggerKey": "transaction"
    },
    {
      "DownstreamPathTemplate": "/api/Referral/conversion-stats",
      "DownstreamScheme": "https",
      "DownstreamHostAndPorts": [
        {
          "Host": "localhost",
          "Port": 443
        }
      ],
      "UpstreamPathTemplate": "/transaction/api/Referral/conversion-stats",
      "UpstreamHttpMethod": [
        "GET"
      ],
      "SwaggerKey": "transaction"
    },
    {
      "DownstreamPathTemplate": "/api/Referral/registrations",
      "DownstreamScheme": "https",
      "DownstreamHostAndPorts": [
        {
          "Host": "localhost",
          "Port": 443
        }
      ],
      "UpstreamPathTemplate": "/transaction/api/Referral/registrations",
      "UpstreamHttpMethod": [
        "GET"
      ],
      "SwaggerKey": "transaction"
    },
    {
      "DownstreamPathTemplate": "/api/Referral/purchases",
      "DownstreamScheme": "https",
      "DownstreamHostAndPorts": [
        {
          "Host": "localhost",
          "Port": 443
        }
      ],
      "UpstreamPathTemplate": "/transaction/api/Referral/purchases",
      "UpstreamHttpMethod": [
        "GET"
      ],
      "SwaggerKey": "transaction"
    },
    {
      "DownstreamPathTemplate": "/api/Referral/activity",
      "DownstreamScheme": "https",
      "DownstreamHostAndPorts": [
        {
          "Host": "localhost",
          "Port": 443
        }
      ],
      "UpstreamPathTemplate": "/transaction/api/Referral/activity",
      "UpstreamHttpMethod": [
        "GET"
      ],
      "SwaggerKey": "transaction"
    },
    {
      "DownstreamPathTemplate": "/api/Referral/payments",
      "DownstreamScheme": "https",
      "DownstreamHostAndPorts": [
        {
          "Host": "localhost",
          "Port": 443
        }
      ],
      "UpstreamPathTemplate": "/transaction/api/Referral/payments",
      "UpstreamHttpMethod": [
        "GET"
      ],
      "SwaggerKey": "transaction"
    },
    {
      "DownstreamPathTemplate": "/api/Referral/withdrawals",
      "DownstreamScheme": "https",
      "DownstreamHostAndPorts": [
        {
          "Host": "localhost",
          "Port": 443
        }
      ],
      "UpstreamPathTemplate": "/transaction/api/Referral/withdrawals",
      "UpstreamHttpMethod": [
        "GET",
        "POST"
      ],
      "SwaggerKey": "transaction"
    },
    {
      "DownstreamPathTemplate": "/api/Subscription",
      "DownstreamScheme": "https",
      "DownstreamHostAndPorts": [
        {
          "Host": "localhost",
          "Port": 443
        }
      ],
      "UpstreamPathTemplate": "/transaction/api/Subscription",
      "UpstreamHttpMethod": [
        "GET",
        "POST",
        "PUT"
      ],
      "SwaggerKey": "transaction"
    },
    {
      "DownstreamPathTemplate": "/api/Subscription/{id}",
      "DownstreamScheme": "https",
      "DownstreamHostAndPorts": [
        {
          "Host": "localhost",
          "Port": 443
        }
      ],
      "UpstreamPathTemplate": "/transaction/api/Subscription/{id}",
      "UpstreamHttpMethod": [
        "GET",
        "DELETE"
      ],
      "SwaggerKey": "transaction"
    },
    {
      "DownstreamPathTemplate": "/api/TronWebhook",
      "DownstreamScheme": "https",
      "DownstreamHostAndPorts": [
        {
          "Host": "localhost",
          "Port": 443
        }
      ],
      "UpstreamPathTemplate": "/transaction/api/TronWebhook",
      "UpstreamHttpMethod": [
        "POST"
      ],
      "SwaggerKey": "transaction"
    },
    {
      "DownstreamPathTemplate": "/api/Wallet",
      "DownstreamScheme": "https",
      "DownstreamHostAndPorts": [
        {
          "Host": "localhost",
          "Port": 443
        }
      ],
      "UpstreamPathTemplate": "/transaction/api/Wallet",
      "UpstreamHttpMethod": [
        "GET",
        "POST",
        "PUT"
      ],
      "SwaggerKey": "transaction"
    },
    {
      "DownstreamPathTemplate": "/api/Wallet/{id}",
      "DownstreamScheme": "https",
      "DownstreamHostAndPorts": [
        {
          "Host": "localhost",
          "Port": 443
        }
      ],
      "UpstreamPathTemplate": "/transaction/api/Wallet/{id}",
      "UpstreamHttpMethod": [
        "GET",
        "DELETE"
      ],
      "SwaggerKey": "transaction"
    },
    {
      "DownstreamPathTemplate": "/api/Admin/dashboard",
      "DownstreamScheme": "https",
      "DownstreamHostAndPorts": [
        {
          "Host": "localhost",
          "Port": 443
        }
      ],
      "UpstreamPathTemplate": "/identity/api/Admin/dashboard",
      "UpstreamHttpMethod": [
        "GET"
      ],
      "SwaggerKey": "identity",
      "AuthenticationOptions": {
        "AuthenticationProviderKey": "Bearer",
        "AllowedScopes": []
      },
      "RouteClaimsRequirement": {
        "role": "Admin"
      }
    },
    {
      "DownstreamPathTemplate": "/api/Auth/register",
      "DownstreamScheme": "https",
      "DownstreamHostAndPorts": [
        {
          "Host": "localhost",
          "Port": 443
        }
      ],
      "UpstreamPathTemplate": "/identity/api/Auth/register",
      "UpstreamHttpMethod": [
        "POST"
      ],
      "SwaggerKey": "identity"
    },
    {
      "DownstreamPathTemplate": "/api/Auth/login",
      "DownstreamScheme": "https",
      "DownstreamHostAndPorts": [
        {
          "Host": "localhost",
          "Port": 443
        }
      ],
      "UpstreamPathTemplate": "/identity/api/Auth/login",
      "UpstreamHttpMethod": [
        "POST"
      ],
      "SwaggerKey": "identity"
    },
    {
      "DownstreamPathTemplate": "/api/Auth/google-login",
      "DownstreamScheme": "https",
      "DownstreamHostAndPorts": [
        {
          "Host": "localhost",
          "Port": 443
        }
      ],
      "UpstreamPathTemplate": "/identity/api/Auth/google-login",
      "UpstreamHttpMethod": [
        "POST"
      ],
      "SwaggerKey": "identity"
    },
    {
      "DownstreamPathTemplate": "/api/Auth/google-register",
      "DownstreamScheme": "https",
      "DownstreamHostAndPorts": [
        {
          "Host": "localhost",
          "Port": 443
        }
      ],
      "UpstreamPathTemplate": "/identity/api/Auth/google-register",
      "UpstreamHttpMethod": [
        "POST"
      ],
      "SwaggerKey": "identity"
    },
    {
      "DownstreamPathTemplate": "/api/Auth/refresh-token",
      "DownstreamScheme": "https",
      "DownstreamHostAndPorts": [
        {
          "Host": "localhost",
          "Port": 443
        }
      ],
      "UpstreamPathTemplate": "/identity/api/Auth/refresh-token",
      "UpstreamHttpMethod": [
        "POST"
      ],
      "SwaggerKey": "identity"
    },
    {
      "DownstreamPathTemplate": "/api/Auth/logout",
      "DownstreamScheme": "https",
      "DownstreamHostAndPorts": [
        {
          "Host": "localhost",
          "Port": 443
        }
      ],
      "UpstreamPathTemplate": "/identity/api/Auth/logout",
      "UpstreamHttpMethod": [
        "POST"
      ],
      "SwaggerKey": "identity"
    },
    {
      "DownstreamPathTemplate": "/api/Auth/forgot-password",
      "DownstreamScheme": "https",
      "DownstreamHostAndPorts": [
        {
          "Host": "localhost",
          "Port": 443
        }
      ],
      "UpstreamPathTemplate": "/identity/api/Auth/forgot-password",
      "UpstreamHttpMethod": [
        "POST"
      ],
      "SwaggerKey": "identity"
    },
    {
      "DownstreamPathTemplate": "/api/Auth/reset-password/{token}",
      "DownstreamScheme": "https",
      "DownstreamHostAndPorts": [
        {
          "Host": "localhost",
          "Port": 443
        }
      ],
      "UpstreamPathTemplate": "/identity/api/Auth/reset-password/{token}",
      "UpstreamHttpMethod": [
        "POST"
      ],
      "SwaggerKey": "identity"
    },
    {
      "DownstreamPathTemplate": "/api/configuration",
      "DownstreamScheme": "https",
      "DownstreamHostAndPorts": [
        {
          "Host": "localhost",
          "Port": 443
        }
      ],
      "UpstreamPathTemplate": "/identity/configuration",
      "UpstreamHttpMethod": [
        "GET",
        "POST"
      ],
      "SwaggerKey": "identity"
    },
    {
      "DownstreamPathTemplate": "/api/outputcache/{region}",
      "DownstreamScheme": "https",
      "DownstreamHostAndPorts": [
        {
          "Host": "localhost",
          "Port": 443
        }
      ],
      "UpstreamPathTemplate": "/identity/outputcache/{region}",
      "UpstreamHttpMethod": [
        "DELETE"
      ],
      "SwaggerKey": "identity"
    },
    {
      "DownstreamPathTemplate": "/api/Role",
      "DownstreamScheme": "https",
      "DownstreamHostAndPorts": [
        {
          "Host": "localhost",
          "Port": 443
        }
      ],
      "UpstreamPathTemplate": "/identity/api/Role",
      "UpstreamHttpMethod": [
        "GET",
        "POST",
        "PUT"
      ],
      "SwaggerKey": "identity",
      "AuthenticationOptions": {
        "AuthenticationProviderKey": "Bearer",
        "AllowedScopes": []
      },
      "RouteClaimsRequirement": {
        "role": "Admin"
      }
    },
    {
      "DownstreamPathTemplate": "/api/Role/{id}",
      "DownstreamScheme": "https",
      "DownstreamHostAndPorts": [
        {
          "Host": "localhost",
          "Port": 443
        }
      ],
      "UpstreamPathTemplate": "/identity/api/Role/{id}",
      "UpstreamHttpMethod": [
        "GET",
        "DELETE"
      ],
      "SwaggerKey": "identity",
      "AuthenticationOptions": {
        "AuthenticationProviderKey": "Bearer",
        "AllowedScopes": []
      },
      "RouteClaimsRequirement": {
        "role": "Admin"
      }
    },
    {
      "DownstreamPathTemplate": "/api/User/info",
      "DownstreamScheme": "https",
      "DownstreamHostAndPorts": [
        {
          "Host": "localhost",
          "Port": 443
        }
      ],
      "UpstreamPathTemplate": "/identity/api/User/info",
      "UpstreamHttpMethod": [
        "GET"
      ],
      "SwaggerKey": "identity"
    },
    {
      "DownstreamPathTemplate": "/api/User",
      "DownstreamScheme": "https",
      "DownstreamHostAndPorts": [
        {
          "Host": "localhost",
          "Port": 443
        }
      ],
      "UpstreamPathTemplate": "/identity/api/User",
      "UpstreamHttpMethod": [
        "GET",
        "PUT"
      ],
      "SwaggerKey": "identity"
    },
    {
      "DownstreamPathTemplate": "/api/User/role",
      "DownstreamScheme": "https",
      "DownstreamHostAndPorts": [
        {
          "Host": "localhost",
          "Port": 443
        }
      ],
      "UpstreamPathTemplate": "/identity/api/User/role",
      "UpstreamHttpMethod": [
        "PUT"
      ],
      "SwaggerKey": "identity",
      "AuthenticationOptions": {
        "AuthenticationProviderKey": "Bearer",
        "AllowedScopes": []
      },
      "RouteClaimsRequirement": {
        "role": "Admin"
      }
    },
    {
      "DownstreamPathTemplate": "/api/User/profile-image",
      "DownstreamScheme": "https",
      "DownstreamHostAndPorts": [
        {
          "Host": "localhost",
          "Port": 443
        }
      ],
      "UpstreamPathTemplate": "/identity/api/User/profile-image",
      "UpstreamHttpMethod": [
        "POST"
      ],
      "SwaggerKey": "identity"
    },
    {
      "DownstreamPathTemplate": "/api/User/send-verification-email",
      "DownstreamScheme": "https",
      "DownstreamHostAndPorts": [
        {
          "Host": "localhost",
          "Port": 443
        }
      ],
      "UpstreamPathTemplate": "/identity/api/User/send-verification-email",
      "UpstreamHttpMethod": [
        "POST"
      ],
      "SwaggerKey": "identity"
    },
    {
      "DownstreamPathTemplate": "/api/User/change-password",
      "DownstreamScheme": "https",
      "DownstreamHostAndPorts": [
        {
          "Host": "localhost",
          "Port": 443
        }
      ],
      "UpstreamPathTemplate": "/identity/api/User/change-password",
      "UpstreamHttpMethod": [
        "POST"
      ],
      "SwaggerKey": "identity"
    },
    {
      "DownstreamPathTemplate": "/api/User/verify",
      "DownstreamScheme": "https",
      "DownstreamHostAndPorts": [
        {
          "Host": "localhost",
          "Port": 443
        }
      ],
      "UpstreamPathTemplate": "/identity/api/User/verify",
      "UpstreamHttpMethod": [
        "GET"
      ],
      "SwaggerKey": "identity"
    },
    {
      "DownstreamPathTemplate": "/api/User/is-email-verified",
      "DownstreamScheme": "https",
      "DownstreamHostAndPorts": [
        {
          "Host": "localhost",
          "Port": 443
        }
      ],
      "UpstreamPathTemplate": "/identity/api/User/is-email-verified",
      "UpstreamHttpMethod": [
        "GET"
      ],
      "SwaggerKey": "identity"
    },
    {
      "DownstreamPathTemplate": "/api/Visit",
      "DownstreamScheme": "https",
      "DownstreamHostAndPorts": [
        {
          "Host": "localhost",
          "Port": 443
        }
      ],
      "UpstreamPathTemplate": "/identity/api/Visit",
      "UpstreamHttpMethod": [
        "POST"
      ],
      "SwaggerKey": "identity"
    },
    {
      "DownstreamPathTemplate": "/api/Blogs",
      "DownstreamScheme": "https",
      "DownstreamHostAndPorts": [
        {
          "Host": "localhost",
          "Port": 443
        }
      ],
      "UpstreamPathTemplate": "/content/api/Blogs",
      "UpstreamHttpMethod": [
        "POST",
        "GET",
        "PUT"
      ],
      "SwaggerKey": "content"
    },
    {
      "DownstreamPathTemplate": "/api/Blogs/{blogId}",
      "DownstreamScheme": "https",
      "DownstreamHostAndPorts": [
        {
          "Host": "localhost",
          "Port": 443
        }
      ],
      "UpstreamPathTemplate": "/content/api/Blogs/{blogId}",
      "UpstreamHttpMethod": [
        "GET",
        "DELETE"
      ],
      "SwaggerKey": "content"
    },
    {
      "DownstreamPathTemplate": "/api/BlogTags",
      "DownstreamScheme": "https",
      "DownstreamHostAndPorts": [
        {
          "Host": "localhost",
          "Port": 443
        }
      ],
      "UpstreamPathTemplate": "/content/api/BlogTags",
      "UpstreamHttpMethod": [
        "POST",
        "GET",
        "PUT"
      ],
      "SwaggerKey": "content"
    },
    {
      "DownstreamPathTemplate": "/api/BlogTags/{tagId}",
      "DownstreamScheme": "https",
      "DownstreamHostAndPorts": [
        {
          "Host": "localhost",
          "Port": 443
        }
      ],
      "UpstreamPathTemplate": "/content/api/BlogTags/{tagId}",
      "UpstreamHttpMethod": [
        "GET",
        "DELETE"
      ],
      "SwaggerKey": "content"
    },
    {
      "DownstreamPathTemplate": "/api/Cases",
      "DownstreamScheme": "https",
      "DownstreamHostAndPorts": [
        {
          "Host": "localhost",
          "Port": 443
        }
      ],
      "UpstreamPathTemplate": "/content/api/Cases",
      "UpstreamHttpMethod": [
        "POST",
        "GET",
        "PUT"
      ],
      "SwaggerKey": "content"
    },
    {
      "DownstreamPathTemplate": "/api/Cases/{CaseId}",
      "DownstreamScheme": "https",
      "DownstreamHostAndPorts": [
        {
          "Host": "localhost",
          "Port": 443
        }
      ],
      "UpstreamPathTemplate": "/content/api/Cases/{CaseId}",
      "UpstreamHttpMethod": [
        "GET",
        "DELETE"
      ],
      "SwaggerKey": "content"
    },
    {
      "DownstreamPathTemplate": "/api/CaseTags",
      "DownstreamScheme": "https",
      "DownstreamHostAndPorts": [
        {
          "Host": "localhost",
          "Port": 443
        }
      ],
      "UpstreamPathTemplate": "/content/api/CaseTags",
      "UpstreamHttpMethod": [
        "POST",
        "GET",
        "PUT"
      ],
      "SwaggerKey": "content"
    },
    {
      "DownstreamPathTemplate": "/api/CaseTags/{tagId}",
      "DownstreamScheme": "https",
      "DownstreamHostAndPorts": [
        {
          "Host": "localhost",
          "Port": 443
        }
      ],
      "UpstreamPathTemplate": "/content/api/CaseTags/{tagId}",
      "UpstreamHttpMethod": [
        "GET",
        "DELETE"
      ],
      "SwaggerKey": "content"
    },
    {
      "DownstreamPathTemplate": "/api/configuration",
      "DownstreamScheme": "https",
      "DownstreamHostAndPorts": [
        {
          "Host": "localhost",
          "Port": 443
        }
      ],
      "UpstreamPathTemplate": "/content/configuration",
      "UpstreamHttpMethod": [
        "GET",
        "POST"
      ],
      "SwaggerKey": "content"
    },
    {
      "DownstreamPathTemplate": "/api/Language",
      "DownstreamScheme": "https",
      "DownstreamHostAndPorts": [
        {
          "Host": "localhost",
          "Port": 443
        }
      ],
      "UpstreamPathTemplate": "/content/api/Language",
      "UpstreamHttpMethod": [
        "GET",
        "POST",
        "PUT"
      ],
      "SwaggerKey": "content"
    },
    {
      "DownstreamPathTemplate": "/api/Language/{id}",
      "DownstreamScheme": "https",
      "DownstreamHostAndPorts": [
        {
          "Host": "localhost",
          "Port": 443
        }
      ],
      "UpstreamPathTemplate": "/content/api/Language/{id}",
      "UpstreamHttpMethod": [
        "GET",
        "DELETE"
      ],
      "SwaggerKey": "content"
    },
    {
      "DownstreamPathTemplate": "/api/Language/flag",
      "DownstreamScheme": "https",
      "DownstreamHostAndPorts": [
        {
          "Host": "localhost",
          "Port": 443
        }
      ],
      "UpstreamPathTemplate": "/content/api/Language/flag",
      "UpstreamHttpMethod": [
        "POST"
      ],
      "SwaggerKey": "content"
    },
    {
      "DownstreamPathTemplate": "/api/Lessons",
      "DownstreamScheme": "https",
      "DownstreamHostAndPorts": [
        {
          "Host": "localhost",
          "Port": 443
        }
      ],
      "UpstreamPathTemplate": "/content/api/Lessons",
      "UpstreamHttpMethod": [
        "POST",
        "GET",
        "PUT"
      ],
      "SwaggerKey": "content"
    },
    {
      "DownstreamPathTemplate": "/api/Lessons/{lessonNumber}",
      "DownstreamScheme": "https",
      "DownstreamHostAndPorts": [
        {
          "Host": "localhost",
          "Port": 443
        }
      ],
      "UpstreamPathTemplate": "/content/api/Lessons/{lessonNumber}",
      "UpstreamHttpMethod": [
        "GET",
        "DELETE"
      ],
      "SwaggerKey": "content"
    },
    {
      "DownstreamPathTemplate": "/api/Lessons/upload-media",
      "DownstreamScheme": "https",
      "DownstreamHostAndPorts": [
        {
          "Host": "localhost",
          "Port": 443
        }
      ],
      "UpstreamPathTemplate": "/content/api/Lessons/upload-media",
      "UpstreamHttpMethod": [
        "POST"
      ],
      "SwaggerKey": "content"
    },
    {
      "DownstreamPathTemplate": "/api/Localization",
      "DownstreamScheme": "https",
      "DownstreamHostAndPorts": [
        {
          "Host": "localhost",
          "Port": 443
        }
      ],
      "UpstreamPathTemplate": "/content/api/Localization",
      "UpstreamHttpMethod": [
        "GET",
        "POST",
        "PUT"
      ],
      "SwaggerKey": "content"
    },
    {
      "DownstreamPathTemplate": "/api/Localization/{id}",
      "DownstreamScheme": "https",
      "DownstreamHostAndPorts": [
        {
          "Host": "localhost",
          "Port": 443
        }
      ],
      "UpstreamPathTemplate": "/content/api/Localization/{id}",
      "UpstreamHttpMethod": [
        "GET",
        "DELETE"
      ],
      "SwaggerKey": "content"
    },
    {
      "DownstreamPathTemplate": "/api/outputcache/{region}",
      "DownstreamScheme": "https",
      "DownstreamHostAndPorts": [
        {
          "Host": "localhost",
          "Port": 443
        }
      ],
      "UpstreamPathTemplate": "/content/outputcache/{region}",
      "UpstreamHttpMethod": [
        "DELETE"
      ],
      "SwaggerKey": "content"
    },
    {
      "DownstreamPathTemplate": "/api/Translation",
      "DownstreamScheme": "https",
      "DownstreamHostAndPorts": [
        {
          "Host": "localhost",
          "Port": 443
        }
      ],
      "UpstreamPathTemplate": "/content/api/Translation",
      "UpstreamHttpMethod": [
        "GET",
        "POST"
      ],
      "SwaggerKey": "content"
    },
    {
      "DownstreamPathTemplate": "/api/Translation/{id}",
      "DownstreamScheme": "https",
      "DownstreamHostAndPorts": [
        {
          "Host": "localhost",
          "Port": 443
        }
      ],
      "UpstreamPathTemplate": "/content/api/Translation/{id}",
      "UpstreamHttpMethod": [
        "GET",
        "PUT",
        "DELETE"
      ],
      "SwaggerKey": "content"
    },
    {
      "DownstreamPathTemplate": "/api/Translation/by-language/{languageId}",
      "DownstreamScheme": "https",
      "DownstreamHostAndPorts": [
        {
          "Host": "localhost",
          "Port": 443
        }
      ],
      "UpstreamPathTemplate": "/content/api/Translation/by-language/{languageId}",
      "UpstreamHttpMethod": [
        "GET"
      ],
      "SwaggerKey": "content"
    },
    {
      "DownstreamPathTemplate": "/api/Tutorials",
      "DownstreamScheme": "https",
      "DownstreamHostAndPorts": [
        {
          "Host": "localhost",
          "Port": 443
        }
      ],
      "UpstreamPathTemplate": "/content/api/Tutorials",
      "UpstreamHttpMethod": [
        "POST",
        "GET",
        "PUT"
      ],
      "SwaggerKey": "content"
    },
    {
      "DownstreamPathTemplate": "/api/Tutorials/{id}",
      "DownstreamScheme": "https",
      "DownstreamHostAndPorts": [
        {
          "Host": "localhost",
          "Port": 443
        }
      ],
      "UpstreamPathTemplate": "/content/api/Tutorials/{id}",
      "UpstreamHttpMethod": [
        "GET",
        "DELETE"
      ],
      "SwaggerKey": "content"
    }
  ],
  "SwaggerEndPoints": [
    {
      "Key": "transaction",
      "Config": [
        {
          "Name": "TransactionService",
          "Version": "v1",
          "Url": "https://localhost:44351/swagger/v1/swagger.json"
        }
      ]
    },
    {
      "Key": "identity",
      "Config": [
        {
          "Name": "IdentityService",
          "Version": "v1",
          "Url": "https://localhost:44350/swagger/v1/swagger.json"
        }
      ]
    },
    {
      "Key": "content",
      "Config": [
        {
          "Name": "ContentService",
          "Version": "v1",
          "Url": "https://localhost:44369/swagger/v1/swagger.json"
        }
      ]
    }
  ],
  "GlobalConfiguration": {
    "BaseUrl": "https://apigateway.local"
  }
}